ncloud_apikey/__init__.py
ncloud_apikey/ncloud_key.py
ncloud_apikey/properties_parser.py
ncloud_apikey-1.0.4.dist-info/METADATA
ncloud_apikey-1.0.4.dist-info/RECORD
ncloud_apikey-1.0.4.dist-info/WHEEL
ncloud_apikey-1.0.4.dist-info/top_level.txt
test/__init__.py
test/test_apikey.py
