Metadata-Version: 2.1
Name: ncloud-apikey
Version: 1.0.4
Summary: apikey
Home-page: UNKNOWN
Author: UNKNOWN
Author-email: UNKNOWN
License: UNKNOWN
Keywords: apikey
Platform: UNKNOWN
